[{"id":1,"title":"Locks","year":"2016-04-29T21:15:37.296Z","poster":"http://lorempixel.com/640/480"},{"id":2,"title":"intranet","year":"2016-06-10T21:04:55.856Z","poster":"http://lorempixel.com/640/480"},{"id":3,"title":"Ways","year":"2016-07-25T02:27:27.537Z","poster":"http://lorempixel.com/640/480"},{"id":4,"title":"Fort","year":"2016-03-08T15:54:12.811Z","poster":"http://lorempixel.com/640/480"},{"id":5,"title":"Turks and Caicos Islands","year":"2016-04-25T15:41:50.451Z","poster":"http://lorempixel.com/640/480"},{"id":6,"title":"Computers","year":"2016-10-23T20:29:49.696Z","poster":"http://lorempixel.com/640/480"},{"id":7,"title":"Cambridgeshire auxiliary","year":"2016-03-31T05:35:28.804Z","poster":"http://lorempixel.com/640/480"},{"id":8,"title":"Comoro Franc wireless","year":"2016-03-25T23:12:40.394Z","poster":"http://lorempixel.com/640/480"},{"id":9,"title":"bleeding-edge","year":"2016-04-23T00:57:38.510Z","poster":"http://lorempixel.com/640/480"},{"id":10,"title":"24/7 recontextualize Regional","year":"2016-04-04T15:39:57.614Z","poster":"http://lorempixel.com/640/480"},{"id":11,"title":"dot-com Gorgeous Metal Pants Soft","year":"2016-11-22T19:33:07.868Z","poster":"http://lorempixel.com/640/480"},{"id":12,"title":"panel","year":"2016-05-12T01:27:38.263Z","poster":"http://lorempixel.com/640/480"},{"id":13,"title":"Maryland","year":"2016-11-30T22:00:57.192Z","poster":"http://lorempixel.com/640/480"},{"id":14,"title":"calculating Designer","year":"2016-05-14T08:23:01.620Z","poster":"http://lorempixel.com/640/480"},{"id":15,"title":"circuit payment","year":"2016-05-10T13:44:41.720Z","poster":"http://lorempixel.com/640/480"},{"id":16,"title":"Bedfordshire secondary","year":"2016-02-12T06:27:58.067Z","poster":"http://lorempixel.com/640/480"},{"id":17,"title":"Consultant Borders","year":"2016-04-21T14:19:58.431Z","poster":"http://lorempixel.com/640/480"},{"id":18,"title":"copy gold","year":"2016-12-17T00:28:41.710Z","poster":"http://lorempixel.com/640/480"},{"id":19,"title":"hacking Creek Movies","year":"2016-09-14T08:26:25.616Z","poster":"http://lorempixel.com/640/480"},{"id":20,"title":"Handcrafted uniform North Carolina","year":"2016-12-04T11:58:44.313Z","poster":"http://lorempixel.com/640/480"},{"id":21,"title":"Delaware","year":"2016-09-25T01:45:08.329Z","poster":"http://lorempixel.com/640/480"},{"id":22,"title":"Buckinghamshire Handcrafted","year":"2016-07-30T08:12:28.132Z","poster":"http://lorempixel.com/640/480"},{"id":23,"title":"Health COM methodologies","year":"2016-07-18T16:53:18.370Z","poster":"http://lorempixel.com/640/480"},{"id":24,"title":"Designer Borders primary","year":"2016-02-24T15:32:48.397Z","poster":"http://lorempixel.com/640/480"},{"id":25,"title":"programming redundant metrics","year":"2016-03-19T15:01:10.845Z","poster":"http://lorempixel.com/640/480"},{"id":26,"title":"invoice Officer","year":"2016-05-08T06:38:09.107Z","poster":"http://lorempixel.com/640/480"},{"id":27,"title":"virtual unleash Chicken","year":"2016-05-06T07:59:34.501Z","poster":"http://lorempixel.com/640/480"},{"id":28,"title":"24/365 knowledge base","year":"2016-09-09T23:34:08.069Z","poster":"http://lorempixel.com/640/480"},{"id":29,"title":"Refined copy digital","year":"2016-03-05T05:57:40.208Z","poster":"http://lorempixel.com/640/480"},{"id":30,"title":"applications deposit","year":"2016-08-19T18:42:28.755Z","poster":"http://lorempixel.com/640/480"},{"id":31,"title":"matrix Bahrain","year":"2016-01-18T10:51:48.893Z","poster":"http://lorempixel.com/640/480"},{"id":32,"title":"Mayotte","year":"2016-06-28T15:53:51.783Z","poster":"http://lorempixel.com/640/480"},{"id":33,"title":"Tanzania Andorra","year":"2016-05-27T22:32:26.473Z","poster":"http://lorempixel.com/640/480"},{"id":34,"title":"interfaces","year":"2016-11-07T22:54:48.735Z","poster":"http://lorempixel.com/640/480"},{"id":35,"title":"experiences PNG","year":"2016-07-04T23:08:44.168Z","poster":"http://lorempixel.com/640/480"},{"id":36,"title":"Sausages attitude-oriented quantifying","year":"2016-11-10T03:19:16.045Z","poster":"http://lorempixel.com/640/480"},{"id":37,"title":"Shirt","year":"2016-08-26T12:25:26.255Z","poster":"http://lorempixel.com/640/480"},{"id":38,"title":"envisioneer matrix invoice","year":"2016-09-11T02:19:15.103Z","poster":"http://lorempixel.com/640/480"},{"id":39,"title":"Mauritius Rupee Vision-oriented","year":"2016-04-30T11:58:51.147Z","poster":"http://lorempixel.com/640/480"},{"id":40,"title":"array Manager Small Granite Cheese","year":"2016-05-11T00:18:09.033Z","poster":"http://lorempixel.com/640/480"},{"id":41,"title":"calculating","year":"2016-11-15T06:02:19.114Z","poster":"http://lorempixel.com/640/480"},{"id":42,"title":"Pizza","year":"2016-02-14T19:24:31.137Z","poster":"http://lorempixel.com/640/480"},{"id":43,"title":"Secured cyan Optimization","year":"2016-12-09T09:37:38.741Z","poster":"http://lorempixel.com/640/480"},{"id":44,"title":"users","year":"2016-08-18T12:51:57.250Z","poster":"http://lorempixel.com/640/480"},{"id":45,"title":"core client-driven Ergonomic Frozen Soap","year":"2016-07-30T12:45:11.731Z","poster":"http://lorempixel.com/640/480"},{"id":46,"title":"Tuvalu","year":"2016-03-20T06:59:23.675Z","poster":"http://lorempixel.com/640/480"},{"id":47,"title":"Georgia applications Chief","year":"2016-10-13T16:34:11.938Z","poster":"http://lorempixel.com/640/480"},{"id":48,"title":"Re-engineered Chair","year":"2016-06-03T14:02:18.032Z","poster":"http://lorempixel.com/640/480"},{"id":49,"title":"Bedfordshire","year":"2016-10-06T10:14:29.025Z","poster":"http://lorempixel.com/640/480"},{"id":50,"title":"Facilitator","year":"2016-05-15T14:41:33.691Z","poster":"http://lorempixel.com/640/480"},{"id":51,"title":"Diverse cross-platform Gloves","year":"2016-12-24T00:59:40.826Z","poster":"http://lorempixel.com/640/480"},{"id":52,"title":"Computer Division","year":"2016-04-01T18:41:38.656Z","poster":"http://lorempixel.com/640/480"},{"id":53,"title":"copying Illinois Washington","year":"2016-07-27T22:03:49.814Z","poster":"http://lorempixel.com/640/480"},{"id":54,"title":"calculate","year":"2016-07-23T17:04:12.419Z","poster":"http://lorempixel.com/640/480"},{"id":55,"title":"Human Bike","year":"2016-03-31T16:28:03.555Z","poster":"http://lorempixel.com/640/480"},{"id":56,"title":"Belize Dollar Lari Wooden","year":"2016-11-11T08:40:45.669Z","poster":"http://lorempixel.com/640/480"},{"id":57,"title":"teal","year":"2016-05-14T22:31:35.835Z","poster":"http://lorempixel.com/640/480"},{"id":58,"title":"circuit sensor","year":"2016-06-06T04:11:18.699Z","poster":"http://lorempixel.com/640/480"},{"id":59,"title":"capability Ergonomic synthesize","year":"2016-02-26T18:46:31.376Z","poster":"http://lorempixel.com/640/480"},{"id":60,"title":"Computers Divide Re-contextualized","year":"2016-05-17T11:25:35.446Z","poster":"http://lorempixel.com/640/480"},{"id":61,"title":"Palestinian Territory Small card","year":"2016-03-05T01:20:01.560Z","poster":"http://lorempixel.com/640/480"},{"id":62,"title":"Rubber","year":"2016-08-25T18:41:38.394Z","poster":"http://lorempixel.com/640/480"},{"id":63,"title":"Bedfordshire Credit Card Account orchestrate","year":"2016-01-17T04:29:55.732Z","poster":"http://lorempixel.com/640/480"},{"id":64,"title":"Mill Latvian Lats","year":"2016-01-23T01:51:58.602Z","poster":"http://lorempixel.com/640/480"},{"id":65,"title":"Identity","year":"2016-03-17T17:36:22.356Z","poster":"http://lorempixel.com/640/480"},{"id":66,"title":"Markets Parkways","year":"2016-03-13T00:41:37.335Z","poster":"http://lorempixel.com/640/480"},{"id":67,"title":"Garden navigating","year":"2016-12-10T01:26:52.261Z","poster":"http://lorempixel.com/640/480"},{"id":68,"title":"leverage open-source International","year":"2016-03-01T09:09:47.128Z","poster":"http://lorempixel.com/640/480"},{"id":69,"title":"backing up","year":"2016-06-29T08:21:27.414Z","poster":"http://lorempixel.com/640/480"},{"id":70,"title":"Assistant withdrawal hardware","year":"2016-08-13T11:28:55.134Z","poster":"http://lorempixel.com/640/480"},{"id":71,"title":"quantifying","year":"2016-07-13T00:17:00.497Z","poster":"http://lorempixel.com/640/480"},{"id":72,"title":"Tunisia Bedfordshire","year":"2016-06-13T19:39:52.549Z","poster":"http://lorempixel.com/640/480"},{"id":73,"title":"Designer input Investor","year":"2016-12-19T14:23:01.929Z","poster":"http://lorempixel.com/640/480"},{"id":74,"title":"whiteboard synergies","year":"2016-12-14T16:27:00.452Z","poster":"http://lorempixel.com/640/480"},{"id":75,"title":"withdrawal","year":"2016-04-28T17:35:13.195Z","poster":"http://lorempixel.com/640/480"},{"id":76,"title":"object-oriented","year":"2016-01-25T15:34:33.045Z","poster":"http://lorempixel.com/640/480"},{"id":77,"title":"Belarus project","year":"2016-12-24T06:38:45.625Z","poster":"http://lorempixel.com/640/480"},{"id":78,"title":"synthesize","year":"2016-04-18T23:00:52.576Z","poster":"http://lorempixel.com/640/480"},{"id":79,"title":"plum Tasty Fresh Bacon","year":"2016-04-11T18:05:23.683Z","poster":"http://lorempixel.com/640/480"},{"id":80,"title":"Locks","year":"2016-07-13T22:28:20.558Z","poster":"http://lorempixel.com/640/480"},{"id":81,"title":"withdrawal","year":"2016-10-31T04:12:39.500Z","poster":"http://lorempixel.com/640/480"},{"id":82,"title":"bypassing Germany compress","year":"2016-08-25T06:12:21.693Z","poster":"http://lorempixel.com/640/480"},{"id":83,"title":"Handmade XSS","year":"2016-08-24T06:19:24.015Z","poster":"http://lorempixel.com/640/480"},{"id":84,"title":"Intelligent Concrete Hat synthesize Sausages","year":"2016-02-04T17:03:39.878Z","poster":"http://lorempixel.com/640/480"},{"id":85,"title":"Burg Turnpike","year":"2016-03-02T06:15:24.869Z","poster":"http://lorempixel.com/640/480"},{"id":86,"title":"Industrial Rustic Australian Dollar","year":"2016-04-30T01:47:21.545Z","poster":"http://lorempixel.com/640/480"},{"id":87,"title":"upward-trending embrace Steel","year":"2016-12-10T19:40:16.381Z","poster":"http://lorempixel.com/640/480"},{"id":88,"title":"Wooden Movies Shoes","year":"2016-03-09T04:39:29.601Z","poster":"http://lorempixel.com/640/480"},{"id":89,"title":"IB","year":"2016-03-23T10:25:13.612Z","poster":"http://lorempixel.com/640/480"},{"id":90,"title":"Rubber withdrawal","year":"2016-09-09T05:53:57.900Z","poster":"http://lorempixel.com/640/480"},{"id":91,"title":"mint green deposit","year":"2016-06-18T08:26:04.392Z","poster":"http://lorempixel.com/640/480"},{"id":92,"title":"Infrastructure Singapore Dollar synthesizing","year":"2016-12-28T21:47:51.793Z","poster":"http://lorempixel.com/640/480"},{"id":93,"title":"Marketing","year":"2016-12-26T03:00:04.798Z","poster":"http://lorempixel.com/640/480"},{"id":94,"title":"coherent","year":"2016-05-05T06:10:19.185Z","poster":"http://lorempixel.com/640/480"},{"id":95,"title":"Supervisor","year":"2016-04-16T20:29:08.050Z","poster":"http://lorempixel.com/640/480"},{"id":96,"title":"solid state","year":"2016-05-07T19:35:58.871Z","poster":"http://lorempixel.com/640/480"},{"id":97,"title":"payment teal","year":"2016-02-22T10:49:18.462Z","poster":"http://lorempixel.com/640/480"},{"id":98,"title":"Nevada","year":"2016-09-11T05:09:29.442Z","poster":"http://lorempixel.com/640/480"},{"id":99,"title":"Washington pixel","year":"2016-11-24T11:25:54.658Z","poster":"http://lorempixel.com/640/480"}]